[
    {
        "category":"forever",
        "id": 1,
        "img": "https://upload.wikimedia.org/wikipedia/he/e/ed/%D7%97%D7%99%D7%99_%D7%A4%D7%90%D7%99.jpg",
        "alt": "המלצה לספר חיי פיי",
        "review" :"חיי פיי. אם הספר הזה עומד במבחן הטעם הדומה - אז כנראה שיש על מה. אפילו את הפתיחה הטרחנית שלו אהבתי וכשהסיפור מתחיל - זה כבר עוצר נשימה, כולל רגע אחד מופרך שלא משנה כמה פעמים אקרא את הספר, תמיד יגרום לי למרר בבכי. ספר חובה."
    } ,

    {
        "category":"forever",
        "id": 2,
        "img": "https://www.am-oved.co.il/Media/Uploads/%D7%A2%D7%98%D7%99%D7%A4%D7%94_-_%D7%A9%D7%A0%D7%AA_%D7%94%D7%91%D7%A9%D7%A8%D7%99%D7%9D_%D7%A9%D7%9C%D7%99(2).jpg",
        "alt": "שנת הבשרים שלי",
        "review" :" שנת הבשרים שלי.     קראתי את הספר לפני שנים,בגדול זה על מסע של אשה בתעשיית הבשר האמריקאית. נשמע טרחני ומעייף? אז זהו, שלא. אחרי שסיימתי את הספר לא נגעתי בבשר 15 שנה, כך שאפשר בהחלט להגיד שזה ספר משנה חיים. וחוץ מזה הוא מהמם. לקרוא דחוף"
    } ,

    {
        "category":"forever",
        "id": 3,
        "img": "https://simania.co.il/bookimages/covers93/938935.jpg",
        "alt": "בא לעולם",
        "review": "בא לעולם. אמאל'ה איזה ספר - יירסק לכם את הלב. ראו הוזהרתם. סיפור אהבה גדול מהחיים ובלי טיפת קיטש (יסלחו לי ג'וג'ו מוייס וחברותיה)על רקע מלחמת האזרחים ביגוסלביה. ספר מושלם"

    }  ,

    {
        "category":"week",
        "id": 4,
        "img": "https://www.e-vrit.co.il/Images/Products/covers_2019_b/torathakvutzot_master.jpg",
        "alt": "תורת הקבוצות",
        "review": "תורת הקבוצות. ספר הפתעה. בלי שום ציפיות ועם התחלה קצת משעממת, הוא תופס תאוצה למשהו באמת מיוחד,סיפור בן יותר מ-400 עמודים שמתרחש בשני מקומות מנוגדים לגמרי- לונדון וראשון לציון (או שזה היה בת ים?) כל כך ישראלי, וכל כך לא ומסתבר שזאת סופרת שזה רומן הביכורים שלה. הקנאה!"
    } 
    
   
]